<?xml version="1.0"?>
<Adversary xmlns:xsi="http://www.w3.org/2001/XMLSchema-instance" xmlns:xsd="http://www.w3.org/2001/XMLSchema">
  <LastChanged>2014-10-01T10:39:14.723</LastChanged>
  <NotPersisted>false</NotPersisted>
  <FileName>Adver500.xml</FileName>
  <Name>Dorrian Vodani, Dressellian Pilot</Name>
  <Key>9bf78d68-e065-412b-bbda-456131bb55bc</Key>
  <Description />
  <Category>Onslaught at Arda I</Category>
  <Characteristics>
    <CharCharacteristic>
      <Key>BR</Key>
      <Name>Brawn</Name>
      <Description />
      <Source />
      <Sources />
      <Custom>Base</Custom>
      <Rank>
        <ForSkills>false</ForSkills>
        <ForChars>false</ForChars>
        <StartingRanks>1</StartingRanks>
        <SpeciesRanks>0</SpeciesRanks>
        <CareerRanks>0</CareerRanks>
        <TalentRanks>0</TalentRanks>
        <ObligationRanks>0</ObligationRanks>
        <DutyRanks>0</DutyRanks>
        <AttachRanks>0</AttachRanks>
        <ItemRanks>0</ItemRanks>
        <CyberRanks>0</CyberRanks>
        <PurchasedRanks>0</PurchasedRanks>
        <CharRanks>0</CharRanks>
        <InjuryRanks>0</InjuryRanks>
      </Rank>
    </CharCharacteristic>
    <CharCharacteristic>
      <Key>AG</Key>
      <Name>Agility</Name>
      <Description />
      <Source />
      <Sources />
      <Custom>Base</Custom>
      <Rank>
        <ForSkills>false</ForSkills>
        <ForChars>false</ForChars>
        <StartingRanks>1</StartingRanks>
        <SpeciesRanks>0</SpeciesRanks>
        <CareerRanks>0</CareerRanks>
        <TalentRanks>0</TalentRanks>
        <ObligationRanks>0</ObligationRanks>
        <DutyRanks>0</DutyRanks>
        <AttachRanks>0</AttachRanks>
        <ItemRanks>0</ItemRanks>
        <CyberRanks>0</CyberRanks>
        <PurchasedRanks>2</PurchasedRanks>
        <CharRanks>0</CharRanks>
        <InjuryRanks>0</InjuryRanks>
      </Rank>
    </CharCharacteristic>
    <CharCharacteristic>
      <Key>INT</Key>
      <Name>Intellect</Name>
      <Description />
      <Source />
      <Sources />
      <Custom>Base</Custom>
      <Rank>
        <ForSkills>false</ForSkills>
        <ForChars>false</ForChars>
        <StartingRanks>1</StartingRanks>
        <SpeciesRanks>0</SpeciesRanks>
        <CareerRanks>0</CareerRanks>
        <TalentRanks>0</TalentRanks>
        <ObligationRanks>0</ObligationRanks>
        <DutyRanks>0</DutyRanks>
        <AttachRanks>0</AttachRanks>
        <ItemRanks>0</ItemRanks>
        <CyberRanks>0</CyberRanks>
        <PurchasedRanks>2</PurchasedRanks>
        <CharRanks>0</CharRanks>
        <InjuryRanks>0</InjuryRanks>
      </Rank>
    </CharCharacteristic>
    <CharCharacteristic>
      <Key>CUN</Key>
      <Name>Cunning</Name>
      <Description />
      <Source />
      <Sources />
      <Custom>Base</Custom>
      <Rank>
        <ForSkills>false</ForSkills>
        <ForChars>false</ForChars>
        <StartingRanks>1</StartingRanks>
        <SpeciesRanks>0</SpeciesRanks>
        <CareerRanks>0</CareerRanks>
        <TalentRanks>0</TalentRanks>
        <ObligationRanks>0</ObligationRanks>
        <DutyRanks>0</DutyRanks>
        <AttachRanks>0</AttachRanks>
        <ItemRanks>0</ItemRanks>
        <CyberRanks>0</CyberRanks>
        <PurchasedRanks>1</PurchasedRanks>
        <CharRanks>0</CharRanks>
        <InjuryRanks>0</InjuryRanks>
      </Rank>
    </CharCharacteristic>
    <CharCharacteristic>
      <Key>WIL</Key>
      <Name>Willpower</Name>
      <Description />
      <Source />
      <Sources />
      <Custom>Base</Custom>
      <Rank>
        <ForSkills>false</ForSkills>
        <ForChars>false</ForChars>
        <StartingRanks>1</StartingRanks>
        <SpeciesRanks>0</SpeciesRanks>
        <CareerRanks>0</CareerRanks>
        <TalentRanks>0</TalentRanks>
        <ObligationRanks>0</ObligationRanks>
        <DutyRanks>0</DutyRanks>
        <AttachRanks>0</AttachRanks>
        <ItemRanks>0</ItemRanks>
        <CyberRanks>0</CyberRanks>
        <PurchasedRanks>1</PurchasedRanks>
        <CharRanks>0</CharRanks>
        <InjuryRanks>0</InjuryRanks>
      </Rank>
    </CharCharacteristic>
    <CharCharacteristic>
      <Key>PR</Key>
      <Name>Presence</Name>
      <Description />
      <Source />
      <Sources />
      <Custom>Base</Custom>
      <Rank>
        <ForSkills>false</ForSkills>
        <ForChars>false</ForChars>
        <StartingRanks>1</StartingRanks>
        <SpeciesRanks>0</SpeciesRanks>
        <CareerRanks>0</CareerRanks>
        <TalentRanks>0</TalentRanks>
        <ObligationRanks>0</ObligationRanks>
        <DutyRanks>0</DutyRanks>
        <AttachRanks>0</AttachRanks>
        <ItemRanks>0</ItemRanks>
        <CyberRanks>0</CyberRanks>
        <PurchasedRanks>1</PurchasedRanks>
        <CharRanks>0</CharRanks>
        <InjuryRanks>0</InjuryRanks>
      </Rank>
    </CharCharacteristic>
  </Characteristics>
  <Talents>
    <CharTalent>
      <Key>FINETUN</Key>
      <Col>0</Col>
      <Row>0</Row>
      <Purchased>false</Purchased>
      <Free>false</Free>
      <Ranks>2</Ranks>
      <BonusChars />
      <Sources />
      <CareerSkills />
      <SelectedSkills />
    </CharTalent>
  </Talents>
  <ForceAbilities />
  <Skills>
    <CharSkill>
      <Key>COMP</Key>
      <Name />
      <Description />
      <Source />
      <Sources />
      <Custom>Base</Custom>
      <Rank>
        <ForSkills>false</ForSkills>
        <ForChars>false</ForChars>
        <StartingRanks>0</StartingRanks>
        <SpeciesRanks>0</SpeciesRanks>
        <CareerRanks>0</CareerRanks>
        <TalentRanks>0</TalentRanks>
        <ObligationRanks>0</ObligationRanks>
        <DutyRanks>0</DutyRanks>
        <AttachRanks>0</AttachRanks>
        <ItemRanks>0</ItemRanks>
        <CyberRanks>0</CyberRanks>
        <PurchasedRanks>1</PurchasedRanks>
        <CharRanks>0</CharRanks>
        <InjuryRanks>0</InjuryRanks>
      </Rank>
      <isCareer>false</isCareer>
      <CharKeyOverride />
    </CharSkill>
    <CharSkill>
      <Key>COORD</Key>
      <Name />
      <Description />
      <Source />
      <Sources />
      <Custom>Base</Custom>
      <Rank>
        <ForSkills>false</ForSkills>
        <ForChars>false</ForChars>
        <StartingRanks>0</StartingRanks>
        <SpeciesRanks>0</SpeciesRanks>
        <CareerRanks>0</CareerRanks>
        <TalentRanks>0</TalentRanks>
        <ObligationRanks>0</ObligationRanks>
        <DutyRanks>0</DutyRanks>
        <AttachRanks>0</AttachRanks>
        <ItemRanks>0</ItemRanks>
        <CyberRanks>0</CyberRanks>
        <PurchasedRanks>2</PurchasedRanks>
        <CharRanks>0</CharRanks>
        <InjuryRanks>0</InjuryRanks>
      </Rank>
      <isCareer>false</isCareer>
      <CharKeyOverride />
    </CharSkill>
    <CharSkill>
      <Key>PILOTSP</Key>
      <Name />
      <Description />
      <Source />
      <Sources />
      <Custom>Base</Custom>
      <Rank>
        <ForSkills>false</ForSkills>
        <ForChars>false</ForChars>
        <StartingRanks>0</StartingRanks>
        <SpeciesRanks>0</SpeciesRanks>
        <CareerRanks>0</CareerRanks>
        <TalentRanks>0</TalentRanks>
        <ObligationRanks>0</ObligationRanks>
        <DutyRanks>0</DutyRanks>
        <AttachRanks>0</AttachRanks>
        <ItemRanks>0</ItemRanks>
        <CyberRanks>0</CyberRanks>
        <PurchasedRanks>3</PurchasedRanks>
        <CharRanks>0</CharRanks>
        <InjuryRanks>0</InjuryRanks>
      </Rank>
      <isCareer>false</isCareer>
      <CharKeyOverride />
    </CharSkill>
  </Skills>
  <Experience>
    <ExperienceRanks>
      <ForSkills>false</ForSkills>
      <ForChars>false</ForChars>
      <StartingRanks>0</StartingRanks>
      <SpeciesRanks>0</SpeciesRanks>
      <CareerRanks>0</CareerRanks>
      <TalentRanks>0</TalentRanks>
      <ObligationRanks>0</ObligationRanks>
      <DutyRanks>0</DutyRanks>
      <AttachRanks>0</AttachRanks>
      <ItemRanks>0</ItemRanks>
      <CyberRanks>0</CyberRanks>
      <PurchasedRanks>0</PurchasedRanks>
      <CharRanks>0</CharRanks>
      <InjuryRanks>0</InjuryRanks>
    </ExperienceRanks>
    <UsedExperience>160</UsedExperience>
  </Experience>
  <Attributes>
    <SoakValue>
      <ForSkills>false</ForSkills>
      <ForChars>false</ForChars>
      <StartingRanks>0</StartingRanks>
      <SpeciesRanks>0</SpeciesRanks>
      <CareerRanks>0</CareerRanks>
      <TalentRanks>0</TalentRanks>
      <ObligationRanks>0</ObligationRanks>
      <DutyRanks>0</DutyRanks>
      <AttachRanks>0</AttachRanks>
      <ItemRanks>0</ItemRanks>
      <CyberRanks>0</CyberRanks>
      <PurchasedRanks>0</PurchasedRanks>
      <CharRanks>1</CharRanks>
      <InjuryRanks>0</InjuryRanks>
    </SoakValue>
    <WoundThreshold>
      <ForSkills>false</ForSkills>
      <ForChars>false</ForChars>
      <StartingRanks>10</StartingRanks>
      <SpeciesRanks>0</SpeciesRanks>
      <CareerRanks>0</CareerRanks>
      <TalentRanks>0</TalentRanks>
      <ObligationRanks>0</ObligationRanks>
      <DutyRanks>0</DutyRanks>
      <AttachRanks>0</AttachRanks>
      <ItemRanks>0</ItemRanks>
      <CyberRanks>0</CyberRanks>
      <PurchasedRanks>0</PurchasedRanks>
      <CharRanks>1</CharRanks>
      <InjuryRanks>0</InjuryRanks>
    </WoundThreshold>
    <StrainThreshold>
      <ForSkills>false</ForSkills>
      <ForChars>false</ForChars>
      <StartingRanks>0</StartingRanks>
      <SpeciesRanks>0</SpeciesRanks>
      <CareerRanks>0</CareerRanks>
      <TalentRanks>0</TalentRanks>
      <ObligationRanks>0</ObligationRanks>
      <DutyRanks>0</DutyRanks>
      <AttachRanks>0</AttachRanks>
      <ItemRanks>0</ItemRanks>
      <CyberRanks>0</CyberRanks>
      <PurchasedRanks>0</PurchasedRanks>
      <CharRanks>2</CharRanks>
      <InjuryRanks>0</InjuryRanks>
    </StrainThreshold>
    <DefenseRanged>
      <ForSkills>false</ForSkills>
      <ForChars>false</ForChars>
      <StartingRanks>0</StartingRanks>
      <SpeciesRanks>0</SpeciesRanks>
      <CareerRanks>0</CareerRanks>
      <TalentRanks>0</TalentRanks>
      <ObligationRanks>0</ObligationRanks>
      <DutyRanks>0</DutyRanks>
      <AttachRanks>0</AttachRanks>
      <ItemRanks>0</ItemRanks>
      <CyberRanks>0</CyberRanks>
      <PurchasedRanks>0</PurchasedRanks>
      <CharRanks>0</CharRanks>
      <InjuryRanks>0</InjuryRanks>
    </DefenseRanged>
    <DefenseMelee>
      <ForSkills>false</ForSkills>
      <ForChars>false</ForChars>
      <StartingRanks>0</StartingRanks>
      <SpeciesRanks>0</SpeciesRanks>
      <CareerRanks>0</CareerRanks>
      <TalentRanks>0</TalentRanks>
      <ObligationRanks>0</ObligationRanks>
      <DutyRanks>0</DutyRanks>
      <AttachRanks>0</AttachRanks>
      <ItemRanks>0</ItemRanks>
      <CyberRanks>0</CyberRanks>
      <PurchasedRanks>0</PurchasedRanks>
      <CharRanks>0</CharRanks>
      <InjuryRanks>0</InjuryRanks>
    </DefenseMelee>
    <ForceRating>
      <ForSkills>false</ForSkills>
      <ForChars>false</ForChars>
      <StartingRanks>0</StartingRanks>
      <SpeciesRanks>0</SpeciesRanks>
      <CareerRanks>0</CareerRanks>
      <TalentRanks>0</TalentRanks>
      <ObligationRanks>0</ObligationRanks>
      <DutyRanks>0</DutyRanks>
      <AttachRanks>0</AttachRanks>
      <ItemRanks>0</ItemRanks>
      <CyberRanks>0</CyberRanks>
      <PurchasedRanks>0</PurchasedRanks>
      <CharRanks>0</CharRanks>
      <InjuryRanks>0</InjuryRanks>
    </ForceRating>
  </Attributes>
  <Weapons>
    <CharWeapon>
      <ItemKey>BLASTPIS</ItemKey>
      <Key>e483f694-3c8a-4509-8a2c-b84f6abefc32</Key>
      <Equipped>true</Equipped>
      <Held>false</Held>
      <Count>1</Count>
      <PurchasedAttachments />
      <AddlHP>0</AddlHP>
      <Notes />
      <Rename />
      <TwoWeaponSets />
      <Shown>false</Shown>
      <Innate>false</Innate>
    </CharWeapon>
  </Weapons>
  <Armor />
  <Gear />
  <Abilities />
  <Items />
  <SpecialWeapons />
  <SpecialArmor>
    <AdvArmor>
      <Key>0</Key>
      <Name>Flight suit</Name>
      <Description />
      <Source />
      <Sources />
      <Custom>Base</Custom>
      <Soak>0</Soak>
      <Defense>0</Defense>
    </AdvArmor>
  </SpecialArmor>
  <AutoRecalc>true</AutoRecalc>
  <Type>Rival</Type>
</Adversary>